main.py
genaimath-1.1.0.dist-info/METADATA
genaimath-1.1.0.dist-info/WHEEL
genaimath-1.1.0.dist-info/top_level.txt
genaimath-1.1.0.dist-info/RECORD
