Metadata-Version: 2.4
Name: genaimath
Version: 1.1.0
Summary: Advanced mathematical operations with arbitrary-precision arithmetic numbers, powered by AI. It supports limitless range of numbers.
Author: SoftwareApkDev
Author-email: SoftwareApkDev <softwareapkdev2022@gmail.com>
Project-URL: Repository, https://github.com/SoftwareApkDev/genaimath
Requires-Python: >=3.7
Dynamic: author
Dynamic: requires-python
